MANIFEST.in
README.rst
setup.py
clicore/__init__.py
clicore/clihelper.py
clicore/cliitem.py
clicore/core.py
clicore.egg-info/PKG-INFO
clicore.egg-info/SOURCES.txt
clicore.egg-info/dependency_links.txt
clicore.egg-info/requires.txt
clicore.egg-info/top_level.txt
test/test.py