Metadata-Version: 1.0
Name: clicore
Version: 0.00.02
Summary: cli core library for python
Home-page: https://github.com/timofurrer/cli
Author: Timo Furrer
Author-email: tuxtimo@gmail.com
License: UNKNOWN
Platform: UNKNOWN
